[
  {"t":"2024-08-14T09:18:33.3236955Z","mt":"Grote paniek","l":"Error","tr":"3eec4b37d6a6cdf68397c6164d126349","sp":"38cf7ea05f3e51a5","ActionId":"f0915413-44e7-4ca0-9cfc-63189bbd83c9","ActionName":"FlexiApi.Controllers.AuthController.ValidateToken (FlexiApi)","RequestId":"0HN5S888SGU8F:00000001","RequestPath":"/api/Auth/valid","ConnectionId":"0HN5S888SGU8F","ApplicationName":"FlexiApi"},
  {"t":"2024-08-14T09:18:33.3948189Z","mt":"HTTP {RequestMethod} {RequestPath} responded {StatusCode} in {Elapsed:0.0000} ms","r":["153.2453"],"tr":"3eec4b37d6a6cdf68397c6164d126349","sp":"38cf7ea05f3e51a5","RequestMethod":"GET","RequestPath":"/api/Auth/valid","StatusCode":200,"Elapsed":153.2453,"SourceContext":"Serilog.AspNetCore.RequestLoggingMiddleware","RequestId":"0HN5S888SGU8F:00000001","ConnectionId":"0HN5S888SGU8F","ApplicationName":"FlexiApi"},
  {"t":"2024-08-14T09:33:56.6441738Z","mt":"Checking token validity","tr":"46a7686b694bf87b4344c6a0dae6d38f","sp":"52b568d13d1920cb","ActionId":"b0e2e6ba-08a1-4cec-8cca-131471ee2485","ActionName":"FlexiApi.Controllers.AuthController.ValidateToken (FlexiApi)","RequestId":"0HN5S888SGU8H:00000001","RequestPath":"/api/Auth/valid","ConnectionId":"0HN5S888SGU8H","ApplicationName":"FlexiApi"},
  {"t":"2024-08-14T09:33:56.6457842Z","mt":"Token is valid: {isValid}","tr":"46a7686b694bf87b4344c6a0dae6d38f","sp":"52b568d13d1920cb","isValid":false,"ActionId":"b0e2e6ba-08a1-4cec-8cca-131471ee2485","ActionName":"FlexiApi.Controllers.AuthController.ValidateToken (FlexiApi)","RequestId":"0HN5S888SGU8H:00000001","RequestPath":"/api/Auth/valid","ConnectionId":"0HN5S888SGU8H","ApplicationName":"FlexiApi"},
  {"t":"2024-08-14T09:33:56.6491756Z","mt":"HTTP {RequestMethod} {RequestPath} responded {StatusCode} in {Elapsed:0.0000} ms","r":["13.1026"],"tr":"46a7686b694bf87b4344c6a0dae6d38f","sp":"52b568d13d1920cb","RequestMethod":"GET","RequestPath":"/api/Auth/valid","StatusCode":200,"Elapsed":13.1026,"SourceContext":"Serilog.AspNetCore.RequestLoggingMiddleware","RequestId":"0HN5S888SGU8H:00000001","ConnectionId":"0HN5S888SGU8H","ApplicationName":"FlexiApi"}
]